upbitpy/__init__.py
upbitpy/upbitpy.py
upbitpy-1.0.dist-info/LICENSE
upbitpy-1.0.dist-info/METADATA
upbitpy-1.0.dist-info/WHEEL
upbitpy-1.0.dist-info/top_level.txt
upbitpy-1.0.dist-info/RECORD
